display_video_360/__init__.py
display_video_360/display_video.py
display_video_360/google_api.py
tests/__init__.py
display_video_360-0.0.1.dist-info/METADATA
display_video_360-0.0.1.dist-info/WHEEL
display_video_360-0.0.1.dist-info/top_level.txt
display_video_360-0.0.1.dist-info/RECORD
