Metadata-Version: 2.1
Name: display-video-360
Version: 0.0.1
Summary: UNKNOWN
Home-page: https://github.com/baspenny/display-video-360
License: UNKNOWN
Platform: UNKNOWN
Requires-Python: >=3.7
Requires-Dist: google-api-python-client
Requires-Dist: httplib2
Requires-Dist: oauth2client
